cosmocrat/__init__.py
cosmocrat/action_validators.py
cosmocrat/custom_argument_parser.py
cosmocrat/definitions.py
cosmocrat/helper_functions.py
cosmocrat/start.py
cosmocrat/osm_tools/__init__.py
cosmocrat/osm_tools/osmconvert.py
cosmocrat/osm_tools/osmosis.py
cosmocrat/osm_tools/osmupdate.py
cosmocrat/sub_parsers/__init__.py
cosmocrat/sub_parsers/apply.py
cosmocrat/sub_parsers/clip.py
cosmocrat/sub_parsers/delta.py
cosmocrat/sub_parsers/drop.py
cosmocrat/sub_parsers/update.py
tests/helpers/__init__.py
tests/helpers/helpers.py
tests/test_osm_tools/__init__.py
tests/test_osm_tools/test_osmconvert.py
tests/test_osm_tools/test_osmosis.py
tests/test_osm_tools/test_osmupdate.py
cosmocrat_cli-1.0.0.dist-info/METADATA
cosmocrat_cli-1.0.0.dist-info/WHEEL
cosmocrat_cli-1.0.0.dist-info/entry_points.txt
cosmocrat_cli-1.0.0.dist-info/top_level.txt
cosmocrat_cli-1.0.0.dist-info/RECORD
