Metadata-Version: 2.1
Name: cosmocrat-cli
Version: 1.0.0
Summary: osm tools wrapper cli
Home-page: https://github.com/MapColonies/cosmocrat-cli
Author: MapColonies
Author-email: mapcolonies@gmail.com
License: UNKNOWN
Platform: UNKNOWN
Classifier: Programming Language :: Python :: 3
Classifier: License :: OSI Approved :: MIT License
Classifier: Operating System :: OS Independent
Requires-Python: >=3.6
Requires-Dist: osmeterium (==0.0.3)
Requires-Dist: mapcoloniesjsonlogger (==1.0.0)
Requires-Dist: validators
